appframer/__init__.py
appframer/app.py
appframer/devices/iphone5.png
appframer/devices/iphone6plus.png
appframer/fonts/Champagne & Limousines Bold.ttf
appframer/fonts/ufonts.com_arial-ce.ttf
appframer-1.0.2.dist-info/DESCRIPTION.rst
appframer-1.0.2.dist-info/METADATA
appframer-1.0.2.dist-info/RECORD
appframer-1.0.2.dist-info/WHEEL
appframer-1.0.2.dist-info/entry_points.txt
appframer-1.0.2.dist-info/metadata.json
appframer-1.0.2.dist-info/top_level.txt
