Metadata-Version: 2.0
Name: appframer
Version: 1.0.2
Summary: AppFramer helps to put your app screenshots in beautiful device frames with annotations by running a simple command.
Home-page: https://github.com/olucurious/AppFramer
Author: Emmanuel Adegbite
Author-email: olucurious@gmail.com
License: MIT License
Keywords: ios,android,screenshot,app frame,screenshot framer,itunes assets,googleplay assets
Platform: UNKNOWN
Classifier: Development Status :: 5 - Production/Stable
Classifier: Intended Audience :: Developers
Classifier: Operating System :: OS Independent
Classifier: Programming Language :: Python
Classifier: License :: OSI Approved :: MIT License
Classifier: Topic :: Communications
Classifier: Topic :: Internet
Classifier: Topic :: Software Development :: Libraries :: Python Modules
Classifier: Topic :: Utilities
Classifier: Programming Language :: Python
Classifier: Programming Language :: Python :: 2
Classifier: Programming Language :: Python :: 2.6
Classifier: Programming Language :: Python :: 2.7
Classifier: Programming Language :: Python :: 3
Classifier: Programming Language :: Python :: 3.2
Classifier: Programming Language :: Python :: 3.3
Classifier: Programming Language :: Python :: 3.4
Classifier: Programming Language :: Python :: 3.5
Requires-Dist: Pillow
Requires-Dist: six (>=1.10.0)
